blockapily/__init__.py
blockapily-0.1.0.dist-info/METADATA
blockapily-0.1.0.dist-info/WHEEL
blockapily-0.1.0.dist-info/RECORD
